LICENSE
MANIFEST.in
README.rst
bumpy.py
setup.py
bin/bump
bin/bumpy
bumpy.egg-info/PKG-INFO
bumpy.egg-info/SOURCES.txt
bumpy.egg-info/dependency_links.txt
bumpy.egg-info/top_level.txt