Metadata-Version: 1.0
Name: bumpy
Version: 0.4.3
Summary: Create build files and CLI tools easily.
Home-page: http://github.com/scizzorz/bumpy
Author: John Weachock
Author-email: jweachock@gmail.com
License: MIT
Platform: UNKNOWN
